hackip/GeoLiteCity.dat
hackip/__init__.py
hackip/__main__.py
hackip/assistant/__init__.py
hackip/assistant/utils.py
hackip/chat.py
hackip/constants.py
hackip/helpers/__init__.py
hackip/logger_config.py
hackip/platforms/__init__.py
hackip/platforms/base.py
hackip/platforms/os.py
hackip/platforms/scanners/__init__.py
hackip/platforms/scanners/helpers.py
hackip/platforms/scanners/nmap_port_scanner.py
hackip/platforms/scanners/port_scanners.py
hackip/platforms/utilities/__init__.py
hackip/platforms/utilities/decorators.py
hackip/platforms/utilities/enum.py
hack_ip-2.9.6.dist-info/LICENSE
hack_ip-2.9.6.dist-info/METADATA
hack_ip-2.9.6.dist-info/WHEEL
hack_ip-2.9.6.dist-info/entry_points.txt
hack_ip-2.9.6.dist-info/RECORD
