Metadata-Version: 2.1
Name: hack-ip
Version: 2.9.6
Summary: This is a tool to get IP and system information of a specific device
Home-page: https://github.com/subhomoy-roy-choudhury/Hack_IP
License: MIT
Keywords: IP,system-info,networking
Author: Subhomoy Roy Choudhury
Author-email: subhomoyrchoudhury@gmail.com
Requires-Python: >=3.9,<4.0
Classifier: Intended Audience :: Developers
Classifier: License :: OSI Approved :: MIT License
Classifier: Operating System :: OS Independent
Classifier: Programming Language :: Python :: 3
Classifier: Programming Language :: Python :: 3.9
Classifier: Programming Language :: Python :: 3.10
Classifier: Programming Language :: Python :: 3.11
Classifier: Programming Language :: Python :: 3.12
Classifier: Topic :: Software Development :: Libraries :: Python Modules
Requires-Dist: art (>=6.1,<7.0)
Requires-Dist: maxminddb-geolite2 (>=2018.703,<2019.0)
Requires-Dist: netifaces (>=0.11.0,<0.12.0)
Requires-Dist: openai (>=1.6.1,<2.0.0)
Requires-Dist: psutil (>=5.9.0,<6.0.0)
Requires-Dist: python-nmap (>=0.7.1,<0.8.0)
Requires-Dist: requests (>=2.28.1,<3.0.0)
Requires-Dist: rich (>=12.6.0,<13.0.0)
Project-URL: Repository, https://github.com/subhomoy-roy-choudhury/Hack_IP
